Release/_impl.cp39-win_amd64.exp
Release/_impl.cp39-win_amd64.lib
stt/__init__.py
stt/_impl.cp39-win_amd64.pyd
stt/client.py
stt/impl.py
stt/lib/libstt.so
stt_tflite-0.10.0a10.dist-info/METADATA
stt_tflite-0.10.0a10.dist-info/WHEEL
stt_tflite-0.10.0a10.dist-info/entry_points.txt
stt_tflite-0.10.0a10.dist-info/top_level.txt
stt_tflite-0.10.0a10.dist-info/RECORD
