Metadata-Version: 2.1
Name: stt-tflite
Version: 0.10.0a10
Summary: A library for doing speech recognition using a Coqui STT model
Home-page: https://github.com/coqui-ai/STT
Author: Coqui GmbH
License: MPL-2.0
Project-URL: Documentation, https://stt.readthedocs.io
Project-URL: Tracker, https://github.com/coqui-ai/STT/issues
Project-URL: Repository, https://github.com/coqui-ai/STT/tree/v0.10.0-alpha.10
Project-URL: Discussions, https://github.com/coqui-ai/STT/discussions
Platform: UNKNOWN
Classifier: Development Status :: 3 - Alpha
Classifier: Environment :: Console
Classifier: Intended Audience :: Developers
Classifier: Intended Audience :: Science/Research
Classifier: License :: OSI Approved :: Mozilla Public License 2.0 (MPL 2.0)
Classifier: Programming Language :: Python :: 2.7
Classifier: Programming Language :: Python :: 3.4
Classifier: Programming Language :: Python :: 3.5
Classifier: Programming Language :: Python :: 3.6
Classifier: Topic :: Multimedia :: Sound/Audio :: Speech
Classifier: Topic :: Scientific/Engineering :: Human Machine Interfaces
Classifier: Topic :: Scientific/Engineering
Classifier: Topic :: Utilities
Requires-Dist: numpy (<1.14.5,>=1.12.0)
